bsmdoc/__init__.py
bsmdoc/__main__.py
bsmdoc/bsmdoc.py
bsmdoc/parsetab.py
bsmdoc/template/template.bsmdoc
bsmdoc/template/css/bsmdoc.css
bsmdoc/template/css/menu.css
bsmdoc/template/js/bsmdoc.js
bsmdoc/template/js/menu.js
bsmdoc-0.0.9.dist-info/LICENSE
bsmdoc-0.0.9.dist-info/METADATA
bsmdoc-0.0.9.dist-info/WHEEL
bsmdoc-0.0.9.dist-info/entry_points.txt
bsmdoc-0.0.9.dist-info/top_level.txt
bsmdoc-0.0.9.dist-info/RECORD
