Metadata-Version: 2.1
Name: bsmdoc
Version: 0.0.9
Summary: another technical html doc generator
Home-page: http://bsmdoc.feiyilin.com
Author: Tianzhu Qiao
Author-email: tq@feiyilin.com
License: MIT
Platform: any
Requires-Python: >=3.2
License-File: LICENSE
Requires-Dist: ply
Requires-Dist: pygments
Requires-Dist: click
Requires-Dist: click-default-group
Requires-Dist: cchardet
Requires-Dist: six
